defdap/__init__.py
defdap/_accelerated.py
defdap/_version.py
defdap/base.py
defdap/crystal.py
defdap/crystal_utils.py
defdap/ebsd.py
defdap/experiment.py
defdap/file_readers.py
defdap/file_writers.py
defdap/hrdic.py
defdap/inspector.py
defdap/plotting.py
defdap/quat.py
defdap/utils.py
defdap/slip_systems/cubic_bcc.txt
defdap/slip_systems/cubic_bcc_110only.txt
defdap/slip_systems/cubic_fcc.txt
defdap/slip_systems/cubic_fcc_damask.txt
defdap/slip_systems/hexagonal_noca.txt
defdap/slip_systems/hexagonal_withca.txt
defdap-1.1.2.dist-info/licenses/LICENSE
docs/source/conf.py
defdap-1.1.2.dist-info/METADATA
defdap-1.1.2.dist-info/WHEEL
defdap-1.1.2.dist-info/top_level.txt
defdap-1.1.2.dist-info/RECORD
