Metadata-Version: 2.4
Name: DefDAP
Version: 1.1.2
Summary: A python library for correlating EBSD and HRDIC data.
Author: Rhys Thomas, João Quinta da Fonseca
Author-email: "Michael D. Atkinson" <michael.atkinson@ukaea.uk>
License: Apache-2.0
Project-URL: GitHub, https://github.com/MechMicroMan/DefDAP
Project-URL: Documentation, https://defdap.readthedocs.io/en/latest
Keywords: EBSD,HRDIC,deformation,crystal,correlative analysis
Classifier: Intended Audience :: Science/Research
Classifier: Topic :: Scientific/Engineering
Classifier: Topic :: Scientific/Engineering :: Information Analysis
Classifier: Development Status :: 5 - Production/Stable
Classifier: Natural Language :: English
Classifier: Operating System :: OS Independent
Classifier: Programming Language :: Python :: 3
Classifier: Programming Language :: Python :: 3.8
Classifier: Programming Language :: Python :: 3.9
Classifier: Programming Language :: Python :: 3.10
Classifier: Programming Language :: Python :: 3.11
Classifier: Framework :: IPython
Classifier: Framework :: Jupyter
Classifier: Framework :: Matplotlib
Requires-Python: >=3.8
License-File: LICENSE
Requires-Dist: scipy>=1.9
Requires-Dist: numpy
Requires-Dist: matplotlib>=3.0.0
Requires-Dist: scikit-image>=0.19
Requires-Dist: pandas
Requires-Dist: peakutils
Requires-Dist: matplotlib_scalebar
Requires-Dist: networkx
Requires-Dist: numba
Provides-Extra: testing
Requires-Dist: pytest<8; extra == "testing"
Requires-Dist: coverage; extra == "testing"
Requires-Dist: pytest-cov; extra == "testing"
Requires-Dist: pytest_cases; extra == "testing"
Provides-Extra: docs
Requires-Dist: sphinx==5.0.2; extra == "docs"
Requires-Dist: sphinx_rtd_theme==0.5.0; extra == "docs"
Requires-Dist: sphinx_autodoc_typehints==1.11.1; extra == "docs"
Requires-Dist: nbsphinx==0.9.3; extra == "docs"
Requires-Dist: ipykernel; extra == "docs"
Requires-Dist: pandoc; extra == "docs"
Requires-Dist: ipympl; extra == "docs"
Dynamic: license-file
